gitmb.py
git_multi_branch-0.3.1.dist-info/LICENSE
git_multi_branch-0.3.1.dist-info/METADATA
git_multi_branch-0.3.1.dist-info/WHEEL
git_multi_branch-0.3.1.dist-info/entry_points.txt
git_multi_branch-0.3.1.dist-info/top_level.txt
git_multi_branch-0.3.1.dist-info/RECORD
