Metadata-Version: 2.1
Name: git-multi-branch
Version: 0.3.1
Summary: Clone all branches of a git repository
Home-page: https://github.com/bacox/git-multi-branch  
Author: bacox
Author-email: bacox.dev@gmail.com
License: UNKNOWN
Platform: UNKNOWN
Classifier: Programming Language :: Python :: 3
Classifier: License :: OSI Approved :: MIT License
Classifier: Operating System :: OS Independent
Requires-Dist: click
Requires-Dist: gitpython
Requires-Dist: gitdb2
